MANIFEST.in
README.txt
setup.py
collective/__init__.py
collective.viewportletmanager.egg-info/PKG-INFO
collective.viewportletmanager.egg-info/SOURCES.txt
collective.viewportletmanager.egg-info/dependency_links.txt
collective.viewportletmanager.egg-info/entry_points.txt
collective.viewportletmanager.egg-info/namespace_packages.txt
collective.viewportletmanager.egg-info/not-zip-safe
collective.viewportletmanager.egg-info/requires.txt
collective.viewportletmanager.egg-info/top_level.txt
collective/viewportletmanager/__init__.py
collective/viewportletmanager/config.py
collective/viewportletmanager/configure.zcml
collective/viewportletmanager/interfaces.py
collective/viewportletmanager/manager.py
collective/viewportletmanager/overrides.zcml
collective/viewportletmanager/portletcontext.py
collective/viewportletmanager/retriever.py
collective/viewportletmanager/setuphandlers.py
collective/viewportletmanager/testing.py
collective/viewportletmanager/browser/__init__.py
collective/viewportletmanager/browser/configure.zcml
collective/viewportletmanager/browser/editmanager.py
collective/viewportletmanager/browser/interfaces.py
collective/viewportletmanager/browser/manage.py
collective/viewportletmanager/browser/traversal.py
collective/viewportletmanager/browser/templates/edit-manager-contextual.pt
collective/viewportletmanager/browser/templates/manage-view-link.pt
collective/viewportletmanager/browser/templates/manage-view.pt
collective/viewportletmanager/profiles/default/browserlayer.xml
collective/viewportletmanager/profiles/default/import_steps.xml
collective/viewportletmanager/profiles/default/metadata.xml
collective/viewportletmanager/profiles/default/viewportletmanager_various.txt
collective/viewportletmanager/tests/__init__.py
collective/viewportletmanager/tests/common.py
collective/viewportletmanager/tests/test_browser.py
collective/viewportletmanager/tests/test_portletcontext.py
collective/viewportletmanager/tests/test_portletretriever.py
collective/viewportletmanager/tests/test_traversal.py
collective/viewportletmanager/tests/test_viewportletsmanagerrenderer.py
docs/HISTORY.txt
docs/INSTALL.txt
docs/LICENSE.GPL
docs/LICENSE.txt