Metadata-Version: 1.0
Name: collective.viewportletmanager
Version: 1.0
Summary: Allows assigning portlets on per view basis.
Home-page: http://svn.plone.org/svn/collective/collective.viewportletmanager
Author: Vitaliy Podoba
Author-email: vitaliy@martinschoel.com
License: GPL
Keywords: plone portlet view
Platform: UNKNOWN
Classifier: Framework :: Plone
Classifier: Programming Language :: Python
